build/lib/build/lib/package/__init__.py
build/lib/build/lib/package/agricultural_field_detector.py
build/lib/build/lib/package/image_tools.py
build/lib/build/lib/package/index_operations.py
build/lib/build/lib/package/lib_image.py
build/lib/build/lib/package/parser.py
build/lib/build/lib/package/run.py
build/lib/build/lib/test/tests.py
build/lib/package/__init__.py
build/lib/package/agricultural_field_detector.py
build/lib/package/image_tools.py
build/lib/package/index_operations.py
build/lib/package/lib_image.py
build/lib/package/parser.py
build/lib/package/run.py
build/lib/test/tests.py
package/__init__.py
package/agricultural_field_detector.py
package/image_tools.py
package/index_operations.py
package/lib_image.py
package/parser.py
package/run.py
test/tests.py
agdetector-1.0.0.dist-info/METADATA
agdetector-1.0.0.dist-info/WHEEL
agdetector-1.0.0.dist-info/entry_points.txt
agdetector-1.0.0.dist-info/top_level.txt
agdetector-1.0.0.dist-info/RECORD
