Metadata-Version: 2.1
Name: agdetector
Version: 1.0.0
Summary: agricultural_field_detector
Home-page: https://jhonalex06.github.io/Jhon_Galindo/
Author: Jhon Galindo
Author-email: jhonalex.ue@gmail.com
Keywords: agricultural field detector python package jhonalex06
Classifier: Programming Language :: Python :: 3
Classifier: License :: OSI Approved :: MIT License
Classifier: Operating System :: OS Independent
Requires-Dist: affine (==2.3.1)
Requires-Dist: attrs (==22.1.0)
Requires-Dist: certifi (==2022.9.24)
Requires-Dist: click (==8.1.3)
Requires-Dist: click-plugins (==1.1.1)
Requires-Dist: cligj (==0.7.2)
Requires-Dist: numpy (==1.23.4)
Requires-Dist: pyparsing (==3.0.9)
Requires-Dist: rasterio (==1.3.3)
Requires-Dist: snuggs (==1.4.7)
